nornir_hier_config/__init__.py
nornir_hier_config/plugins/tasks/__init__.py
nornir_hier_config/plugins/tasks/hier_remediation.py
nornir_hier_config/utilities/__init__.py
nornir_hier_config/utilities/general.py
nornir_hier_config-0.1.0.dist-info/WHEEL
nornir_hier_config-0.1.0.dist-info/METADATA
nornir_hier_config-0.1.0.dist-info/RECORD
