Metadata-Version: 2.1
Name: nornir-hier-config
Version: 0.1.0
Summary: Collection of tasks using the hier-config module.
Home-page: https://github.com/h4ndzdatm0ld/nornir_hier_config
License: Apache-2.0
Keywords: nornir,hier-config,config-remediation
Author: Hugo Tinoco
Author-email: hugotinoco@icloud.com
Requires-Python: >=3.8,<3.10
Classifier: License :: OSI Approved :: Apache Software License
Classifier: Programming Language :: Python :: 3
Classifier: Programming Language :: Python :: 3.8
Classifier: Programming Language :: Python :: 3.9
Requires-Dist: deepdiff (>=5.6.0,<6.0.0)
Project-URL: Documentation, https://tbd
Project-URL: Repository, https://github.com/h4ndzdatm0ld/nornir_hier_config
